spelling/.pyspelling.yml
spelling/__init__.py
spelling/__main__.py
spelling/check.py
spelling/config.py
spelling/dependencies.py
spelling/version.py
spelling/filters/__init__.py
spelling/filters/filtererr.py
spelling-1.2.3.dist-info/METADATA
spelling-1.2.3.dist-info/WHEEL
spelling-1.2.3.dist-info/top_level.txt
spelling-1.2.3.dist-info/RECORD
