Metadata-Version: 2.1
Name: spelling
Version: 1.2.3
Summary: CI configuration engine for pyspelling using plugins like resplendent and unanimous to make CI integration easier.
Home-page: https://github.com/resplendent-dev/spelling
Author: Tim Gates
Author-email: tim.gates@iress.com
Maintainer: Tim Gates
Maintainer-email: tim.gates@iress.com
License: GPLv3+
Classifier: Development Status :: 4 - Beta
Classifier: Programming Language :: Python
Classifier: Programming Language :: Python :: 3
Classifier: Programming Language :: Python :: 3.7
Classifier: Programming Language :: Python :: 3.8
Classifier: Programming Language :: Python :: Implementation :: CPython
Classifier: Programming Language :: Python :: Implementation :: PyPy
Classifier: Operating System :: OS Independent
Classifier: License :: OSI Approved :: GNU General Public License v3 (GPLv3)
Requires-Python: >=3.7
Requires-Dist: whichcraft
Requires-Dist: distro
Requires-Dist: dataset
Requires-Dist: pyspelling
Requires-Dist: wcmatch
Requires-Dist: resplendent
Requires-Dist: unanimous >=0.8.4
Requires-Dist: PyYAML
